python_goto/__init__.py
python_goto/goto.py
python_goto-0.1.4.dist-info/METADATA
python_goto-0.1.4.dist-info/WHEEL
python_goto-0.1.4.dist-info/licence.txt
python_goto-0.1.4.dist-info/top_level.txt
python_goto-0.1.4.dist-info/RECORD
