Metadata-Version: 2.1
Name: python-goto
Version: 0.1.4
Summary: Add goto to Python
Author: The Lumberjack
Author-email: just4now@example.com
Keywords: goto
License-File: licence.txt
